gcs_clients/VERSION
gcs_clients/__init__.py
gcs_clients/base.py
gcs_clients/restclient.py
gcs_clients/test.py
gcs_clients/tests/__init__.py
gcs_clients/tests/test_base.py
gcs_clients/tests/test_restclient.py
uw_gcs_clients-1.0.3.dist-info/LICENSE
uw_gcs_clients-1.0.3.dist-info/METADATA
uw_gcs_clients-1.0.3.dist-info/WHEEL
uw_gcs_clients-1.0.3.dist-info/top_level.txt
uw_gcs_clients-1.0.3.dist-info/RECORD
